pysz/__init__.py
pysz/pyConfig.cp310-win_amd64.pyd
pysz/pyConfig.pxd
pysz/pyConfig.pyx
pysz/pyConfigEnums.py
pysz/sz.cp310-win_amd64.pyd
pysz/sz.pxd
pysz/sz.pyx
pysz-1.0.2.dist-info/licenses/LICENSE
pysz-1.0.2.dist-info/METADATA
pysz-1.0.2.dist-info/WHEEL
pysz-1.0.2.dist-info/top_level.txt
pysz-1.0.2.dist-info/RECORD
