Metadata-Version: 2.4
Name: pysz
Version: 1.0.2
Summary: Python interface for SZ3: An error-bounded lossy compressor for scientific data
Author: SZ3 Team
License: BSD-3-Clause
Project-URL: Homepage, https://github.com/szcompressor/SZ3
Project-URL: Documentation, https://github.com/szcompressor/SZ3/tree/master/tools/pysz
Project-URL: Source, https://github.com/szcompressor/SZ3
Project-URL: Bug Tracker, https://github.com/szcompressor/SZ3/issues
Keywords: compression,scientific data,lossy compression,SZ3,error-bounded
Classifier: Development Status :: 4 - Beta
Classifier: Intended Audience :: Science/Research
Classifier: Intended Audience :: Developers
Classifier: Programming Language :: Python :: 3
Classifier: Programming Language :: Python :: 3.8
Classifier: Programming Language :: Python :: 3.9
Classifier: Programming Language :: Python :: 3.10
Classifier: Programming Language :: Python :: 3.11
Classifier: Programming Language :: Python :: 3.12
Classifier: Programming Language :: C++
Classifier: Programming Language :: Cython
Classifier: Topic :: Scientific/Engineering
Classifier: Topic :: System :: Archiving :: Compression
Classifier: Operating System :: POSIX :: Linux
Classifier: Operating System :: MacOS
Requires-Python: >=3.8
License-File: LICENSE
Requires-Dist: numpy>=1.20.0
Dynamic: license-file
